gtrans/__init__.py
gtrans/browser.py
gtrans/chromedriver
gtrans/gtrans.py
gtrans/uagents.txt
gtrans-0.2.dist-info/DESCRIPTION.rst
gtrans-0.2.dist-info/METADATA
gtrans-0.2.dist-info/RECORD
gtrans-0.2.dist-info/WHEEL
gtrans-0.2.dist-info/metadata.json
gtrans-0.2.dist-info/top_level.txt
