Metadata-Version: 2.0
Name: gtrans
Version: 0.2
Summary: Free Google Translate API service
Home-page: https://github.com/sergei4e/gtrans
Author: Sergii Chernenko
Author-email: 4e.sergei@gmail.com
License: MIT
Keywords: google translate api free python gtrans
Platform: UNKNOWN
Classifier: License :: OSI Approved :: MIT License
Classifier: Intended Audience :: Developers
Classifier: Programming Language :: Python :: 3.6
Classifier: Environment :: Web Environment
Classifier: Development Status :: 3 - Alpha
Requires-Dist: bs4
Requires-Dist: lxml
Requires-Dist: nltk
Requires-Dist: selenium
